pypg/__init__.py
pypg/locator.py
pypg/named.py
pypg/property.py
pypg/property_transcoder.py
pypg/transcode.py
pypg/type_registry.py
pypg/type_utils.py
pypg/traits/__init__.py
pypg/traits/allowed_range.py
pypg/traits/config.py
pypg/traits/member_named.py
pypg/traits/metadata.py
pypg/traits/obligate.py
pypg/traits/observable.py
pypg/traits/overridable.py
pypg/traits/read_only.py
pypg/traits/reference_counted.py
pypg/traits/unit.py
pypg/traits/validated.py
property_graph-2.5.3.dist-info/LICENSE
property_graph-2.5.3.dist-info/METADATA
property_graph-2.5.3.dist-info/WHEEL
property_graph-2.5.3.dist-info/top_level.txt
property_graph-2.5.3.dist-info/RECORD
