Metadata-Version: 2.1
Name: property-graph
Version: 2.5.3
Summary: python library for working with objects as graphs of property data
Author-email: Matt Fowler <mattefowler@gmail.com>
License: Apache License
Keywords: graph,serialization,metadata,property,schema
Classifier: Programming Language :: Python :: 3 :: Only
Classifier: Programming Language :: Python :: 3.10
Classifier: Programming Language :: Python :: 3.11
Classifier: Topic :: Software Development :: Libraries :: Python Modules
Requires-Python: >=3.10
License-File: LICENSE
